examples/__init__.py
examples/bug.py
examples/toy.py
examples/toy2.py
examples/benchmarks/__init__.py
examples/benchmarks/cvrp_augerat.py
examples/benchmarks/cvrptw_solomon.py
examples/benchmarks/mdvrp_cordeau.py
examples/benchmarks/tests_augerat.py
examples/benchmarks/tests_solomon.py
tests/__init__.py
vrpy/__init__.py
vrpy/clark_wright_test.py
vrpy/clarke_wright.py
vrpy/main.py
vrpy/master_solve_pulp.py
vrpy/masterproblem.py
vrpy/subproblem.py
vrpy/subproblem_cspy.py
vrpy/subproblem_greedy.py
vrpy/subproblem_lp.py
vrpy-0.2.0.dist-info/LICENSE
vrpy-0.2.0.dist-info/METADATA
vrpy-0.2.0.dist-info/WHEEL
vrpy-0.2.0.dist-info/top_level.txt
vrpy-0.2.0.dist-info/RECORD
