Metadata-Version: 2.1
Name: vrpy
Version: 0.2.0
Summary: A python framework for solving vehicle routing problems
Home-page: https://github.com/Kuifje02/vrpy
Author: Romain Montagne, David Torres
Author-email: r.montagne@hotmail.fr
License: MIT
Keywords: vehicle routing problem,vrp,column generation
Platform: UNKNOWN
Classifier: Programming Language :: Python :: 3.6
Classifier: Programming Language :: Python :: 3.7
Classifier: Programming Language :: Python :: 3.8
Classifier: License :: OSI Approved :: MIT License
Classifier: Operating System :: OS Independent
Requires-Dist: cspy
Requires-Dist: networkx
Requires-Dist: numpy
Requires-Dist: pulp
